{
  "collapse-filter": false,
  "search": "",
  "showTags": true,
  "showAttachments": false,
  "hideUnresolved": false,
  "showOrphans": true,
  "collapse-color-groups": false,
  "colorGroups": [
    {
      "query": "risk",
      "color": {
        "a": 1,
        "rgb": 14701138
      }
    },
    {
      "query": "#CIS ",
      "color": {
        "a": 1,
        "rgb": 14069084
      }
    }
  ],
  "collapse-display": false,
  "showArrow": false,
  "textFadeMultiplier": 0,
  "nodeSizeMultiplier": 1.55898876404494,
  "lineSizeMultiplier": 3.7061797752809,
  "collapse-forces": false,
  "centerStrength": 0.518713248970312,
  "repelStrength": 20,
  "linkStrength": 1,
  "linkDistance": 107,
  "scale": 1.0000000000000187,
  "close": true
}